utiliT/__init__.py
utiliT/io.py
utiliT-0.0.8.dist-info/LICENSE
utiliT-0.0.8.dist-info/METADATA
utiliT-0.0.8.dist-info/WHEEL
utiliT-0.0.8.dist-info/top_level.txt
utiliT-0.0.8.dist-info/RECORD
