Metadata-Version: 2.1
Name: utiliT
Version: 0.0.8
Summary: Python utilities
Home-page: UNKNOWN
Author: Nakul Upadhya
Author-email: <nakulupadhya1@gmail.com>
License: UNKNOWN
Keywords: python,utilities,fileio
Platform: UNKNOWN
Classifier: Development Status :: 1 - Planning
Classifier: Intended Audience :: Developers
Classifier: Programming Language :: Python :: 3
Classifier: Operating System :: Unix
Classifier: Operating System :: MacOS :: MacOS X
Classifier: Operating System :: Microsoft :: Windows
License-File: LICENSE
Requires-Dist: pyyaml
Requires-Dist: pathlib
Requires-Dist: ez-yaml
